docs/source/conf.py
seasenselib/__init__.py
seasenselib/__main__.py
seasenselib/parameters.py
seasenselib/cli/__init__.py
seasenselib/cli/parser.py
seasenselib/cli/router.py
seasenselib/cli/commands/__init__.py
seasenselib/cli/commands/base.py
seasenselib/cli/commands/data_commands.py
seasenselib/cli/commands/factory.py
seasenselib/cli/commands/info_commands.py
seasenselib/cli/commands/plot_commands.py
seasenselib/core/__init__.py
seasenselib/core/dependencies.py
seasenselib/core/exceptions.py
seasenselib/core/format_detection.py
seasenselib/core/format_registry.py
seasenselib/core/io_manager.py
seasenselib/plotters/__init__.py
seasenselib/plotters/base.py
seasenselib/plotters/profile_plotter.py
seasenselib/plotters/time_series_plotter.py
seasenselib/plotters/time_series_plotter_multi.py
seasenselib/plotters/ts_diagram_plotter.py
seasenselib/processors/__init__.py
seasenselib/processors/base.py
seasenselib/processors/resample_processor.py
seasenselib/processors/statistics_processor.py
seasenselib/processors/subset_processor.py
seasenselib/readers/__init__.py
seasenselib/readers/adcp_matlab_rdadcp_reader.py
seasenselib/readers/adcp_matlab_uhhds_reader.py
seasenselib/readers/base.py
seasenselib/readers/csv_reader.py
seasenselib/readers/netcdf_reader.py
seasenselib/readers/nortek_ascii_reader.py
seasenselib/readers/rbr_ascii_reader.py
seasenselib/readers/rbr_matlab_legacy_reader.py
seasenselib/readers/rbr_matlab_reader.py
seasenselib/readers/rbr_matlab_rsktools_reader.py
seasenselib/readers/rbr_rsk_auto_reader.py
seasenselib/readers/rbr_rsk_legacy_reader.py
seasenselib/readers/rbr_rsk_reader.py
seasenselib/readers/rcm_matlab_reader.py
seasenselib/readers/registry.py
seasenselib/readers/sbe_ascii_reader.py
seasenselib/readers/sbe_cnv_reader.py
seasenselib/readers/seasun_tob_reader.py
seasenselib/writers/__init__.py
seasenselib/writers/base.py
seasenselib/writers/csv_writer.py
seasenselib/writers/excel_writer.py
seasenselib/writers/netcdf_writer.py
seasenselib-0.3.0.dist-info/licenses/LICENSE
tests/__init__.py
seasenselib-0.3.0.dist-info/METADATA
seasenselib-0.3.0.dist-info/WHEEL
seasenselib-0.3.0.dist-info/entry_points.txt
seasenselib-0.3.0.dist-info/top_level.txt
seasenselib-0.3.0.dist-info/RECORD
