Metadata-Version: 2.4
Name: seasenselib
Version: 0.3.0
Summary: Read, convert, and plot oceanographic sensor data from moored instruments.
Author: Eleanor Frajka-Williams, Isabelle Schmitz, Yves Sorge
Maintainer-email: Yves Sorge <yves.sorge@uni-hamburg.de>
License-Expression: AGPL-3.0-only
Project-URL: Homepage, https://ocean-uhh.github.io/seasenselib/
Project-URL: Source_Code, https://github.com/ocean-uhh/seasenselib
Project-URL: Download, https://pypi.org/project/seasenselib/
Keywords: ctd,oceanography,cnv,seabird,rbr,aquadopp,microcat,sensors,moorings,data,netcdf,cf,conventions,tools,plotting,adcp,netcdf
Classifier: Programming Language :: Python :: 3
Classifier: Operating System :: OS Independent
Classifier: Topic :: Scientific/Engineering :: Oceanography
Classifier: Intended Audience :: Science/Research
Classifier: Intended Audience :: Developers
Classifier: Natural Language :: English
Requires-Python: >=3.7
License-File: LICENSE
Requires-Dist: pycnv
Requires-Dist: pandas
Requires-Dist: xarray
Requires-Dist: numpy
Requires-Dist: scipy
Requires-Dist: pylablib
Requires-Dist: matplotlib
Requires-Dist: netcdf4
Requires-Dist: gsw
Requires-Dist: pyrsktools
Requires-Dist: setuptools
Provides-Extra: dev
Requires-Dist: build; extra == "dev"
Requires-Dist: twine; extra == "dev"
Requires-Dist: sphinx; extra == "dev"
Requires-Dist: nbsphinx; extra == "dev"
Requires-Dist: myst-parser; extra == "dev"
Requires-Dist: sphinx_rtd_theme; extra == "dev"
Requires-Dist: pytest; extra == "dev"
Dynamic: license-file
